views_extraction/__init__.py
views_extraction/__main__.py
views_extraction/constants.py
views_extraction/Assets/__init__.py
views_extraction/Assets/lpbi_views_extraction.py
views_extraction/Assets/setup_constants.py
views_extraction/Assets/Auto_Data_Removal/auto_data_removal.py
views_extraction/Assets/Email_Sender/email_sender.py
views_extraction/Assets/Email_Sender/Template/summation_file.txt
views_extraction/Assets/Summation/summation.py
views_extraction/Assets/Summation/summation_main.py
views_extraction/Assets/Webscraping/webscrape_data.py
views_extraction/Assets/Webscraping/webscrape_ids.py
views_extraction/Assets/Webscraping/worker.py
views_extraction/Output/data.json
views_extraction/Output/Invalid_Ids/nothing.txt
views_extraction-1.1.3.dist-info/METADATA
views_extraction-1.1.3.dist-info/WHEEL
views_extraction-1.1.3.dist-info/entry_points.txt
views_extraction-1.1.3.dist-info/top_level.txt
views_extraction-1.1.3.dist-info/RECORD
