Metadata-Version: 2.1
Name: views-extraction
Version: 1.1.3
Summary: This project extracts the view data of every post from WordPress.
Home-page: https://github.com/AbhisarAnand/LPBI-Data-Extraction-Project
Author: Abhisar Anand, Srinivas Sriram
Author-email: abhisar.muz@gmail.com, srinivassriram06@gmail.com
License: UNKNOWN
Platform: UNKNOWN
Classifier: Programming Language :: Python
Classifier: Programming Language :: Python :: 3
Requires-Dist: Cython
Requires-Dist: getpass4
Requires-Dist: selenium
Requires-Dist: pandas
Requires-Dist: webdriver-manager
Requires-Dist: numpy
Requires-Dist: python-dateutil
Requires-Dist: setuptools
Requires-Dist: openpyxl
Requires-Dist: tqdm
Requires-Dist: psutil
Requires-Dist: colorama
Requires-Dist: simple-term-menu
